{
  "kind": "collectionType",
  "collectionName": "calls",
  "info": {
    "singularName": "call",
    "pluralName": "calls",
    "displayName": "Звонки"
  },
  "options": {
    "draftAndPublish": true
  },
  "pluginOptions": {
    "i18n": {
      "localized": true
    }
  },
  "attributes": {
    "name": {
      "pluginOptions": {
        "i18n": {
          "localized": true
        }
      },
      "type": "string",
      "required": true
    },
    "phone": {
      "pluginOptions": {
        "i18n": {
          "localized": true
        }
      },
      "type": "string",
      "required": true
    },
    "done": {
      "pluginOptions": {
        "i18n": {
          "localized": true
        }
      },
      "type": "boolean",
      "default": false,
      "required": true
    }
  }
}
